yuanrl/__init__.py
yuanrl/marl/__init__.py
yuanrl/marl/apis/QMIX.py
yuanrl/marl/apis/__init__.py
yuanrl/marl/nn/QMIXBackbone.py
yuanrl/marl/nn/__init__.py
yuanrl/marl/noise/__init__.py
yuanrl/marl/replayer/QMIXReplayer.py
yuanrl/marl/replayer/__init__.py
yuanrl/sarl/__init__.py
yuanrl/sarl/apis/DDPG.py
yuanrl/sarl/apis/DeepQ.py
yuanrl/sarl/apis/PPO.py
yuanrl/sarl/apis/SACDiscrete.py
yuanrl/sarl/apis/TRPO.py
yuanrl/sarl/apis/__init__.py
yuanrl/sarl/nn/ActorContinuous.py
yuanrl/sarl/nn/ActorDiscrete.py
yuanrl/sarl/nn/CriticStateAction.py
yuanrl/sarl/nn/CriticStateOnly.py
yuanrl/sarl/nn/QNetworkContinuous.py
yuanrl/sarl/nn/QNetworkDiscrete.py
yuanrl/sarl/nn/__init__.py
yuanrl/sarl/noise/OrnsteinUhlenbeckProcess.py
yuanrl/sarl/noise/__init__.py
yuanrl/sarl/replayer/DQNReplayer.py
yuanrl/sarl/replayer/PPOReplayer.py
yuanrl/sarl/replayer/__init__.py
yuanrl-0.0.6.dist-info/LICENSE
yuanrl-0.0.6.dist-info/METADATA
yuanrl-0.0.6.dist-info/WHEEL
yuanrl-0.0.6.dist-info/top_level.txt
yuanrl-0.0.6.dist-info/RECORD
