Metadata-Version: 2.1
Name: yuanrl
Version: 0.0.6
Summary: Implementations of the Single-Agent Reinforcement Learning (SARL) and Multi-Agent Reinforcement Learning (MARL) algorithms.
Home-page: https://github.com/Mingqi-Yuan/YuanRL
Author: Mingqi Yuan
Author-email: friedrichyuan19990827@gmail.com
License: UNKNOWN
Project-URL: Bug Tracker, https://github.com/Mingqi-Yuan/YuanRL/issues
Platform: UNKNOWN
Classifier: Programming Language :: Python :: 3
Classifier: License :: OSI Approved :: MIT License
Classifier: Operating System :: OS Independent
Requires-Python: >=3.6
